{
    "configurations": [
        {
            "name": "Mac",
            "includePath": [
                "${workspaceFolder}/**",
                "${workspaceFolder}/../Common/**",
                "${workspaceFolder}/../Drivers/**"
            ],
            "defines": [
                "CORE_CM7",
                "USE_HAL_DRIVER",
                "STM32H755xx",
                "USE_PWR_DIRECT_SMPS_SUPPLY",
                "USE_NUCLEO_144",
                "_GNU_SOURCE"
            ],
            "compilerPath": "/Applications/STM32CubeIDE.app/Contents/Eclipse/plugins/com.st.stm32cube.ide.mcu.externaltools.gnu-tools-for-stm32.13.3.rel1.macos64_1.0.100.202509120712/tools/bin/arm-none-eabi-gcc",
            "cStandard": "c11",
            "cppStandard": "c++14",
            "intelliSenseMode": "gcc-arm"
        }
    ],
    "version": 4
}
